swnn/__init__.py
swnn/builder.py
swnn/graph2tree.py
swnn/multipartite_graph.py
swnn/utils/__init__.py
swnn/utils/_scale.py
swnn/utils/process.py
swnn-0.1.0.dist-info/LICENSE
swnn-0.1.0.dist-info/METADATA
swnn-0.1.0.dist-info/WHEEL
swnn-0.1.0.dist-info/top_level.txt
swnn-0.1.0.dist-info/RECORD
