Metadata-Version: 2.1
Name: swnn
Version: 0.1.0
Summary: A tool for building developmental tree from scRNA-seq
Home-page: https://github.com/XingyanLiu/stagewiseNN
Author: Xingyan Liu
Author-email: 544568643@qq.com
License: MIT
Platform: UNKNOWN
Classifier: License :: OSI Approved :: MIT License
Classifier: Programming Language :: Python
Classifier: Programming Language :: Python :: 3
Classifier: Programming Language :: Python :: 3.6
Classifier: Programming Language :: Python :: Implementation :: CPython
Classifier: Programming Language :: Python :: Implementation :: PyPy
Requires-Python: >=3.6.0
License-File: LICENSE
Requires-Dist: scanpy
Requires-Dist: scikit-learn
Requires-Dist: scipy
Provides-Extra: downstream_analysis
Requires-Dist: scanpy ; extra == 'downstream_analysis'
